djsonb/__init__.py
djsonb/fields.py
djsonb/lookups.py
djsonb-0.2.3.dist-info/METADATA
djsonb-0.2.3.dist-info/RECORD
djsonb-0.2.3.dist-info/WHEEL
djsonb-0.2.3.dist-info/top_level.txt
tests/__init__.py
tests/manage.py
tests/settings.py
tests/djsonb_fields/__init__.py
tests/djsonb_fields/encoders.py
tests/djsonb_fields/models.py
tests/djsonb_fields/tests.py
tests/djsonb_fields/migrations/0001_initial.py
tests/djsonb_fields/migrations/__init__.py
