Metadata-Version: 2.1
Name: djsonb
Version: 0.2.3
Summary: PostgreSQL json field support for Django.
Home-page: https://github.com/azavea/djsonb
Author: 
Author-email: 
Maintainer: 
Maintainer-email: 
License: BSD
Keywords: django,postgresql,pgsql,jsonb,json,field
Platform: OS Independent
Classifier: Development Status :: 4 - Beta
Classifier: Framework :: Django
Classifier: Intended Audience :: Developers
Classifier: License :: OSI Approved :: BSD License
Classifier: Operating System :: OS Independent
Classifier: Programming Language :: Python
Classifier: Programming Language :: Python :: 2
Classifier: Programming Language :: Python :: 2.7
Classifier: Programming Language :: Python :: 3
Classifier: Programming Language :: Python :: 3.3
Classifier: Topic :: Internet :: WWW/HTTP
Requires-Dist: Django (<1.12)
Requires-Dist: psycopg2 (>=2.6)
